overwatch/__init__.py
overwatch/version.py
overwatch/api/__init__.py
overwatch/api/config.yaml
overwatch/api/fileAccess.py
overwatch/api/fileToHTTP.py
overwatch/base/__init__.py
overwatch/base/config.py
overwatch/base/config.yaml
overwatch/base/dataTransfer.py
overwatch/base/deploy.py
overwatch/base/replay.py
overwatch/base/run.py
overwatch/base/storageWrapper.py
overwatch/base/updateDBUsers.py
overwatch/base/utilities.py
overwatch/processing/__init__.py
overwatch/processing/config.yaml
overwatch/processing/mergeFiles.py
overwatch/processing/pluginManager.py
overwatch/processing/processRuns.py
overwatch/processing/processingClasses.py
overwatch/processing/run.py
overwatch/processing/alarms/__init__.py
overwatch/processing/alarms/aggregatingAlarm.py
overwatch/processing/alarms/alarm.py
overwatch/processing/alarms/collectors.py
overwatch/processing/alarms/example.py
overwatch/processing/alarms/registrator.py
overwatch/processing/alarms/impl/__init__.py
overwatch/processing/alarms/impl/absolutePreviousValueAlarm.py
overwatch/processing/alarms/impl/andAlarm.py
overwatch/processing/alarms/impl/betweenValuesAlarm.py
overwatch/processing/alarms/impl/checkLastNAlarm.py
overwatch/processing/alarms/impl/meanInRangeAlarm.py
overwatch/processing/alarms/impl/orAlarm.py
overwatch/processing/alarms/impl/relativePreviousValueAlarm.py
overwatch/processing/detectors/EMC.py
overwatch/processing/detectors/HLT.py
overwatch/processing/detectors/TPC.py
overwatch/processing/detectors/__init__.py
overwatch/processing/trending/__init__.py
overwatch/processing/trending/constants.py
overwatch/processing/trending/info.py
overwatch/processing/trending/manager.py
overwatch/processing/trending/objects/__init__.py
overwatch/processing/trending/objects/maximum.py
overwatch/processing/trending/objects/mean.py
overwatch/processing/trending/objects/object.py
overwatch/processing/trending/objects/stdDev.py
overwatch/receiver/__init__.py
overwatch/receiver/config.yaml
overwatch/receiver/dqmReceiver.py
aliceoverwatch-1.3.1.dist-info/LICENSE
aliceoverwatch-1.3.1.dist-info/METADATA
aliceoverwatch-1.3.1.dist-info/WHEEL
aliceoverwatch-1.3.1.dist-info/entry_points.txt
aliceoverwatch-1.3.1.dist-info/top_level.txt
aliceoverwatch-1.3.1.dist-info/RECORD
