Metadata-Version: 2.1
Name: aliceoverwatch
Version: 1.3.1
Summary: ALICE OVERWATCH: Online Monitoring via the HLT
Home-page: https://github.com/raymondEhlers/OVERWATCH
Author: Raymond Ehlers
Author-email: raymond.ehlers@cern.ch
License: BSD 3-Clause
Keywords: HEP ALICE
Platform: UNKNOWN
Classifier: Development Status :: 4 - Beta
Classifier: Intended Audience :: Science/Research
Classifier: Programming Language :: Python :: 2.7
Classifier: Programming Language :: Python :: 3.6
Classifier: Programming Language :: Python :: 3.7
Requires-Dist: aenum
Requires-Dist: future
Requires-Dist: pendulum
Requires-Dist: ruamel.yaml
Requires-Dist: numpy
Requires-Dist: werkzeug
Requires-Dist: flask
Requires-Dist: Flask-Login
Requires-Dist: Flask-Assets
Requires-Dist: PyYAML
Requires-Dist: Flask-RESTful
Requires-Dist: ZODB
Requires-Dist: zodburi
Requires-Dist: bcrypt
Requires-Dist: Flask-Bcrypt
Requires-Dist: Flask-WTF
Requires-Dist: requests
Requires-Dist: uwsgi
Requires-Dist: sentry-sdk[flask]
Requires-Dist: slackclient
Provides-Extra: dev
Requires-Dist: flake8 ; extra == 'dev'
Provides-Extra: docs
Requires-Dist: sphinx ; extra == 'docs'
Requires-Dist: recommonmark ; extra == 'docs'
Requires-Dist: sphinx-markdown-tables ; extra == 'docs'
Provides-Extra: tests
Requires-Dist: pytest ; extra == 'tests'
Requires-Dist: pytest-cov ; extra == 'tests'
Requires-Dist: pytest-mock ; extra == 'tests'
Requires-Dist: codecov ; extra == 'tests'
